{"version": 0.6, "generator": "Overpass API 0.7.62.1 084b4234", "osm3s": {"timestamp_osm_base": "2024-09-03T04:44:25Z", "copyright": "The data included in this document is from www.openstreetmap.org. The data is made available under ODbL."}, "elements": [{"type": "node", "id": 3585683520, "lat": -35.6342483, "lon": 144.1297281}, {"type": "node", "id": 3730012967, "lat": -35.6345169, "lon": 144.13043}, {"type": "node", "id": 3730012969, "lat": -35.6350706, "lon": 144.1302234}, {"type": "node", "id": 3730012970, "lat": -35.6257922, "lon": 144.1274392}, {"type": "node", "id": 3730012973, "lat": -35.625995, "lon": 144.1287319}, {"type": "node", "id": 3730012975, "lat": -35.635685, "lon": 144.1294753}, {"type": "node", "id": 3730012980, "lat": -35.6280335, "lon": 144.1284076}, {"type": "node", "id": 3730012985, "lat": -35.6351567, "lon": 144.1288208}, {"type": "node", "id": 3730012987, "lat": -35.6357592, "lon": 144.1302233}, {"type": "node", "id": 3730012992, "lat": -35.6278914, "lon": 144.1271414}, {"type": "node", "id": 3730012995, "lat": -35.6361762, "lon": 144.1302342}, {"type": "node", "id": 4041214342, "lat": -35.6245477, "lon": 144.1318729}, {"type": "node", "id": 4041214345, "lat": -35.6227861, "lon": 144.1330101}, {"type": "node", "id": 4041214346, "lat": -35.6229213, "lon": 144.1343137}, {"type": "node", "id": 4041214347, "lat": -35.6234516, "lon": 144.1328806}, {"type": "node", "id": 4041214348, "lat": -35.6233603, "lon": 144.1320728}, {"type": "node", "id": 4041214349, "lat": -35.6242861, "lon": 144.1295287}, {"type": "node", "id": 4041214350, "lat": -35.6228874, "lon": 144.130839}, {"type": "node", "id": 4041214351, "lat": -35.6230216, "lon": 144.1310509}, {"type": "node", "id": 4041214352, "lat": -35.6230194, "lon": 144.1313566}, {"type": "node", "id": 4041214353, "lat": -35.6226117, "lon": 144.1314867}, {"type": "node", "id": 4041214354, "lat": -35.622446, "lon": 144.1310253}, {"type": "node", "id": 4041214355, "lat": -35.6219968, "lon": 144.1314384}, {"type": "node", "id": 4041214356, "lat": -35.6216338, "lon": 144.1345578}, {"type": "node", "id": 4041214357, "lat": -35.6213362, "lon": 144.1318327}, {"type": "node", "id": 4041216292, "lat": -35.62592, "lon": 144.1280431}, {"type": "node", "id": 4041216293, "lat": -35.6258652, "lon": 144.1280631}, {"type": "node", "id": 5586061195, "lat": -35.4673423, "lon": 144.3929714}, {"type": "node", "id": 5698461568, "lat": -35.46673, "lon": 144.3917656}, {"type": "node", "id": 5698461569, "lat": -35.4666557, "lon": 144.3917495}, {"type": "node", "id": 5698461570, "lat": -35.465581, "lon": 144.3935466}, {"type": "node", "id": 5698461571, "lat": -35.4656553, "lon": 144.394083}, {"type": "node", "id": 5698461572, "lat": -35.4663018, "lon": 144.3946677}, {"type": "node", "id": 9421507439, "lat": -35.6240122, "lon": 144.1319616}, {"type": "node", "id": 9421507440, "lat": -35.6241049, "lon": 144.1319468}, {"type": "node", "id": 9421507469, "lat": -35.624251, "lon": 144.1319222}, {"type": "node", "id": 9421576128, "lat": -35.6229233, "lon": 144.1308956}, {"type": "node", "id": 10102523914, "lat": -35.6363265, "lon": 144.130133}, {"type": "node", "id": 10206279755, "lat": -35.4667956, "lon": 144.3938631}, {"type": "way", "id": 369190554, "nodes": [3730012985, 3585683520, 3730012967, 3730012969, 3730012987, 3730012995, 10102523914, 3730012975, 3730012985], "tags": {"addr:housenumber": "7", "addr:street": "Punt Road", "amenity": "school", "grades": "0-6", "isced:level": "1", "name": "Koondrook Primary School", "operator": "Victorian Department of Education", "operator:type": "public", "operator:wikidata": "Q5260272", "website": "https://www.koondrookps.vic.edu.au/"}}, {"type": "way", "id": 369190556, "nodes": [3730012992, 3730012980, 3730012973, 4041216292, 4041216293, 3730012970, 3730012992], "tags": {"addr:city": "Barham", "addr:postcode": "2732", "amenity": "school", "contact:email": "barham-p.school@det.nsw.edu.au", "contact:fax": "+61 3 5453 2972", "contact:phone": "+61 3 5453 2133", "fee": "no", "grades": "0-6", "isced:level": "1", "name": "Barham Public School", "operator": "NSW Department of Education", "operator:type": "public", "operator:wikidata": "Q5260271", "school:enrolment": "147", "school:gender": "mixed", "school:selective": "no", "school:specialty": "comprehensive", "school:type": "primary", "start_date": "1901-10-01", "website": "https://www.barham-p.schools.nsw.edu.au/"}}, {"type": "way", "id": 401709590, "nodes": [4041214342, 4041214349, 4041214350, 9421576128, 4041214351, 4041214352, 4041214353, 4041214354, 4041214355, 4041214357, 4041214356, 4041214346, 4041214345, 4041214347, 4041214348, 9421507439, 9421507440, 9421507469, 4041214342], "tags": {"addr:city": "Barham", "addr:postcode": "2732", "addr:street": "Gonn Street", "amenity": "school", "contact:email": "barham-h.school@det.nsw.edu.au", "contact:fax": "+61 3 5453 3259", "contact:phone": "+61 3 5453 2322", "fee": "no", "grades": "7-12", "isced:level": "2-3", "name": "Barham High School", "operator": "NSW Department of Education", "operator:type": "public", "operator:wikidata": "Q5260271", "school:enrolment": "150", "school:gender": "mixed", "school:selective": "no", "school:specialty": "comprehensive", "school:type": "secondary", "start_date": "1969-01-01", "website": "https://www.barham-h.schools.nsw.edu.au/"}}, {"type": "way", "id": 598728948, "nodes": [5586061195, 10206279755, 5698461572, 5698461571, 5698461570, 5698461569, 5698461568, 5586061195], "tags": {"addr:city": "Wakool", "addr:housenumber": "49", "addr:postcode": "2710", "addr:street": "Flinders Street", "amenity": "school", "contact:email": "wakool-p.school@det.nsw.edu.au", "contact:fax": "+61 3 5887 1291", "contact:phone": "+61 3 5887 1126", "fee": "no", "grades": "0-6", "isced:level": "1", "name": "Wakool Burraboi Public School", "operator": "NSW Department of Education", "operator:type": "public", "operator:wikidata": "Q5260271", "school:enrolment": "13", "school:gender": "mixed", "school:selective": "no", "school:specialty": "comprehensive", "school:type": "primary", "source:boundary": "LPI Base Map June 2018", "start_date": "1904-07-01", "website": "https://www.wakool-p.schools.nsw.edu.au/"}}]}