{"version": 0.6, "generator": "Overpass API 0.7.62.1 084b4234", "osm3s": {"timestamp_osm_base": "2024-09-03T04:45:28Z", "copyright": "The data included in this document is from www.openstreetmap.org. The data is made available under ODbL."}, "elements": [{"type": "node", "id": 2315478959, "lat": -35.7325764, "lon": 142.3593572}, {"type": "node", "id": 2315478965, "lat": -35.7312929, "lon": 142.3608068}, {"type": "node", "id": 2315478967, "lat": -35.7315846, "lon": 142.3601273}, {"type": "node", "id": 2315478977, "lat": -35.7320009, "lon": 142.3595949}, {"type": "node", "id": 2315478981, "lat": -35.7323709, "lon": 142.359836}, {"type": "node", "id": 2315478985, "lat": -35.7317313, "lon": 142.3602229}, {"type": "node", "id": 2315478990, "lat": -35.7302838, "lon": 142.3578636}, {"type": "node", "id": 2315478994, "lat": -35.729517, "lon": 142.3596499}, {"type": "node", "id": 5385332495, "lat": -35.3442324, "lon": 142.4267942}, {"type": "node", "id": 5385332496, "lat": -35.34425, "lon": 142.4281961}, {"type": "node", "id": 5385332497, "lat": -35.3438454, "lon": 142.4281991}, {"type": "node", "id": 5385332498, "lat": -35.3438504, "lon": 142.4284549}, {"type": "node", "id": 5385332499, "lat": -35.3432623, "lon": 142.4284395}, {"type": "node", "id": 5385332500, "lat": -35.3432674, "lon": 142.4268157}, {"type": "node", "id": 10586138107, "lat": -35.7236817, "lon": 142.3622832}, {"type": "node", "id": 10586138108, "lat": -35.7243304, "lon": 142.3626869}, {"type": "node", "id": 10586138109, "lat": -35.7245202, "lon": 142.3622242}, {"type": "node", "id": 10586138110, "lat": -35.7241731, "lon": 142.3620082}, {"type": "node", "id": 10586138111, "lat": -35.7244254, "lon": 142.3613931}, {"type": "node", "id": 10586138112, "lat": -35.7241238, "lon": 142.3612054}, {"type": "node", "id": 11444147073, "lat": -35.7325074, "lon": 142.3593123}, {"type": "way", "id": 222592369, "nodes": [2315478981, 2315478977, 2315478985, 2315478967, 2315478965, 2315478994, 2315478990, 11444147073, 2315478959, 2315478981], "tags": {"addr:housenumber": "11", "addr:street": "Bruce Street", "amenity": "school", "grades": "0-6", "isced:level": "1", "name": "Hopetoun P-12 College Primary Campus", "operator": "Victorian Department of Education", "operator:type": "public", "operator:wikidata": "Q5260272", "phone": "+61 3 5083 3135", "website": "https://hopetounp12.wordpress.com/"}}, {"type": "way", "id": 558454097, "nodes": [5385332495, 5385332496, 5385332497, 5385332498, 5385332499, 5385332500, 5385332495], "tags": {"addr:housenumber": "13", "addr:street": "Harrison Street", "amenity": "school", "grades": "0-6", "isced:level": "1", "name": "Tempy Primary School", "operator": "Victorian Department of Education", "operator:type": "public", "operator:wikidata": "Q5260272"}}, {"type": "way", "id": 1135628862, "nodes": [10586138112, 10586138111, 10586138110, 10586138109, 10586138108, 10586138107, 10586138112], "tags": {"addr:housenumber": "33", "addr:street": "Lascelles Street", "amenity": "school", "denomination": "catholic", "grades": "0-6", "isced:level": "1", "name": "St Joseph's Primary School", "operator": "Diocese of Ballarat Catholic Education Limited", "operator:short": "DOBCEL", "operator:type": "religious", "operator:wikidata": "Q113059804", "religion": "christian"}}]}